ble2mqtt/__init__.py
ble2mqtt/__main__.py
ble2mqtt/__version__.py
ble2mqtt/ble2mqtt.py
ble2mqtt/compat.py
ble2mqtt/exceptions.py
ble2mqtt/manager.py
ble2mqtt/tasks.py
ble2mqtt/utils.py
ble2mqtt/devices/__init__.py
ble2mqtt/devices/atom_fast.py
ble2mqtt/devices/base.py
ble2mqtt/devices/bulb_avea.py
ble2mqtt/devices/cooker_redmond.py
ble2mqtt/devices/cover_am43.py
ble2mqtt/devices/cover_soma.py
ble2mqtt/devices/flower_mclh09.py
ble2mqtt/devices/flower_miflora.py
ble2mqtt/devices/govee.py
ble2mqtt/devices/kettle_redmond.py
ble2mqtt/devices/kettle_xiaomi.py
ble2mqtt/devices/presence.py
ble2mqtt/devices/qingping_cgdk2.py
ble2mqtt/devices/roidmi_cleaner.py
ble2mqtt/devices/ruuvitag.py
ble2mqtt/devices/switchbot.py
ble2mqtt/devices/thermostat_ensto.py
ble2mqtt/devices/uuids.py
ble2mqtt/devices/voltage_bm2.py
ble2mqtt/devices/vson_air_wp6003.py
ble2mqtt/devices/xiaomi_base.py
ble2mqtt/devices/xiaomi_ht.py
ble2mqtt/devices/xiaomi_lywsd03.py
ble2mqtt/devices/xiaomi_lywsd03_atc.py
ble2mqtt/protocols/__init__.py
ble2mqtt/protocols/am43.py
ble2mqtt/protocols/avea.py
ble2mqtt/protocols/base.py
ble2mqtt/protocols/ensto.py
ble2mqtt/protocols/govee.py
ble2mqtt/protocols/redmond.py
ble2mqtt/protocols/ruuvi.py
ble2mqtt/protocols/soma.py
ble2mqtt/protocols/wp6003.py
ble2mqtt/protocols/xiaomi.py
ble2mqtt-0.2.5.dist-info/licenses/LICENSE
ble2mqtt-0.2.5.dist-info/METADATA
ble2mqtt-0.2.5.dist-info/WHEEL
ble2mqtt-0.2.5.dist-info/entry_points.txt
ble2mqtt-0.2.5.dist-info/top_level.txt
ble2mqtt-0.2.5.dist-info/RECORD
