Metadata-Version: 2.4
Name: ble2mqtt
Version: 0.2.5
Summary: BLE to MQTT bridge
Home-page: https://github.com/devbis/ble2mqtt/
Author: Ivan Belokobylskiy
Author-email: belokobylskij@gmail.com
Classifier: Programming Language :: Python :: 3.7
Classifier: Programming Language :: Python :: 3.8
Classifier: Programming Language :: Python :: 3.9
Classifier: Programming Language :: Python :: 3.10
Classifier: Programming Language :: Python :: 3.11
Classifier: Programming Language :: Python :: 3 :: Only
Classifier: Topic :: Utilities
License-File: LICENSE
Requires-Dist: aio-mqtt-mod>=0.3.0
Requires-Dist: bleak>=0.12.0
Provides-Extra: full
Requires-Dist: pycryptodome; extra == "full"
Dynamic: author
Dynamic: author-email
Dynamic: classifier
Dynamic: description
Dynamic: description-content-type
Dynamic: home-page
Dynamic: license-file
Dynamic: provides-extra
Dynamic: requires-dist
Dynamic: summary
